seg_tgce/__init__.py
seg_tgce/data/__init__.py
seg_tgce/data/crowd_seg/__init__.py
seg_tgce/data/crowd_seg/_retrieve.py
seg_tgce/data/crowd_seg/map.py
seg_tgce/data/crowd_seg/metadata/test_data.json
seg_tgce/data/crowd_seg/metadata/test_inverted.json
seg_tgce/data/crowd_seg/metadata/train_data.json
seg_tgce/data/crowd_seg/metadata/train_inverted.json
seg_tgce/data/crowd_seg/metadata/val_data.json
seg_tgce/data/crowd_seg/metadata/val_inverted.json
seg_tgce/data/crowd_seg/plot_annotations.py
seg_tgce/data/crowd_seg/tfds_builder.py
seg_tgce/data/crowd_seg/types.py
seg_tgce/data/crowd_seg/visualizer.py
seg_tgce/data/oxford_pet/__init__.py
seg_tgce/data/oxford_pet/disturbance/model.py
seg_tgce/data/oxford_pet/oxford_iiit_pet.py
seg_tgce/data/oxford_pet/oxford_pet.py
seg_tgce/data/oxford_pet/oxford_pet_tfds.py
seg_tgce/data/utils.py
seg_tgce/experiments/__init__.py
seg_tgce/experiments/histology/baseline.py
seg_tgce/experiments/histology/features.py
seg_tgce/experiments/histology/pixel.py
seg_tgce/experiments/histology/scalar.py
seg_tgce/experiments/pets/features.py
seg_tgce/experiments/pets/mv.py
seg_tgce/experiments/pets/pixel.py
seg_tgce/experiments/pets/scalar.py
seg_tgce/experiments/pets/staple.py
seg_tgce/experiments/plot_utils.py
seg_tgce/experiments/types.py
seg_tgce/experiments/utils.py
seg_tgce/layers/__init__.py
seg_tgce/loss/__init__.py
seg_tgce/loss/test_tgce.py
seg_tgce/loss/tgce.py
seg_tgce/metrics.py
seg_tgce/models/__init__.py
seg_tgce/models/builders.py
seg_tgce/models/ma_model.py
seg_tgce/models/unet.py
seg_tgce/py.typed
seg_tgce/run/__init__.py
seg_tgce/run/runner.py
seg_tgce-0.3.17.dist-info/METADATA
seg_tgce-0.3.17.dist-info/WHEEL
seg_tgce-0.3.17.dist-info/RECORD
