Metadata-Version: 2.3
Name: seg_tgce
Version: 0.3.17
Summary: Framework for handling image segmentation in the context of multiple annotators
License: MIT License
Author: Brandon Lotero
Author-email: blotero@gmail.com
Maintainer: Brandon Lotero
Maintainer-email: blotero@gmail.com
Requires-Python: >=3.10,<3.13
Classifier: License :: OSI Approved :: MIT License
Classifier: License :: Other/Proprietary License
Classifier: Programming Language :: Python :: 3
Classifier: Programming Language :: Python :: 3.10
Classifier: Programming Language :: Python :: 3.11
Classifier: Programming Language :: Python :: 3.12
Requires-Dist: albumentations (>=2.0.7,<3.0.0)
Requires-Dist: boto3 (>=1.34.130,<2.0.0)
Requires-Dist: kaleido (>=1.0.0,<2.0.0)
Requires-Dist: keras (==3.8.0)
Requires-Dist: keras-hub (>=0.20.0,<0.21.0)
Requires-Dist: keras-tuner[bayesian] (>=1.4.7,<2.0.0)
Requires-Dist: matplotlib (>=3.8.4,<4.0.0)
Requires-Dist: numpy (==2.0.2)
Requires-Dist: opencv-python (>=4.9.0.80,<5.0.0.0)
Requires-Dist: optuna (>=4.4.0,<5.0.0)
Requires-Dist: pandas (>=2.2.3,<3.0.0)
Requires-Dist: plotly (>=6.2.0,<7.0.0)
Requires-Dist: pydot (>=3.0.4,<4.0.0)
Requires-Dist: seaborn (>=0.13.2,<0.14.0)
Requires-Dist: simpleitk (>=2.5.0,<3.0.0)
Requires-Dist: tensorflow (==2.18.0)
Requires-Dist: tensorflow-datasets (==4.9.6)
Project-URL: Documentation, https://seg-tgce.readthedocs.io/en/latest/
Project-URL: Homepage, https://github.com/blotero/seg_tgce
Project-URL: Issues, https://github.com/blotero/seg_tgce/issues
Project-URL: Repository, https://github.com/blotero/seg_tgce
